{"tasks":[{"id":"5bfe2206-a93e-4aff-a34a-ed75cce0e74c","title":"taks12","description":"a common task2","completed_at":null,"created_at":1708392442512,"updated_at":1708392442512},{"id":"c3b996f1-3898-4074-9da3-cda5ab2b8432","title":"taks12","description":"a common task2","completed_at":null,"created_at":1708392443250,"updated_at":1708392443250},{"id":"9f6fca7c-8ee4-4111-8a12-8af7dec908db","title":"Task 01","description":"Descrição da Task 01","completed_at":null,"created_at":1708466022456,"updated_at":1708466022456},{"id":"530e812d-c85a-44f9-b6c3-cd0d33522817","title":"Task 02","description":"Descrição da Task 02","completed_at":null,"created_at":1708466022466,"updated_at":1708466022466},{"id":"bfb0224d-7c7e-4fae-9071-5995e0002b56","title":"Task 03","description":"Descrição da Task 03","completed_at":null,"created_at":1708466022468,"updated_at":1708466022468},{"id":"b6811e67-5dd3-4758-8e3b-6e7894ced3c8","title":"Task 04","description":"Descrição da Task 04","completed_at":null,"created_at":1708466022470,"updated_at":1708466022470},{"id":"5b6152b6-11c0-40bc-9acb-5811b803ae08","title":"Task 05","description":"Descrição da Task 05","completed_at":null,"created_at":1708466022471,"updated_at":1708466022471}]}